metafind/__init__.py
metafind/__main__.py
metafind/cli.py
metafind/client.py
metafind/clientfactory.py
metafind/errors.py
metafind/exifclient.py
metafind/models.py
metafind/output.py
metafind-1.0.1.dist-info/LICENSE
metafind-1.0.1.dist-info/METADATA
metafind-1.0.1.dist-info/WHEEL
metafind-1.0.1.dist-info/entry_points.txt
metafind-1.0.1.dist-info/top_level.txt
metafind-1.0.1.dist-info/RECORD
