Metadata-Version: 2.2
Name: metafind
Version: 1.0.1
Summary: Metadata analysis tool written for CSEC-473 - Penetration Testing
Project-URL: Homepage, https://docs.sapph2c.dev/metafind
Project-URL: Source, https://github.com/sapph2c/metafind
Requires-Python: >=3.13
License-File: LICENSE
Requires-Dist: click>=8.1.8
Requires-Dist: pyexiftool>=0.5.6
Requires-Dist: rich>=13.9.4
